{
    "Ar36": {
        "error": 0.003194813809908643, 
        "error_type": "SEM", 
        "filter_outliers_dict": {
            "filter_outliers": true, 
            "iterations": 2, 
            "std_devs": 2
        }, 
        "fit": "Parabolic", 
        "value": 1.4108927734568923
    }, 
    "Ar37": {
        "error": 0.013541695420559009, 
        "error_type": "SEM", 
        "filter_outliers_dict": {
            "filter_outliers": true, 
            "iterations": 2, 
            "std_devs": 2
        }, 
        "fit": "linear", 
        "value": 0.08513792933612327
    }, 
    "Ar38": {
        "error": 0.004703093879212689, 
        "error_type": "SEM", 
        "filter_outliers_dict": {
            "filter_outliers": true, 
            "iterations": 2, 
            "std_devs": 2
        }, 
        "fit": "linear", 
        "value": 1.5001877991557846
    }, 
    "Ar39": {
        "error": 0.028944139814204014, 
        "error_type": "SEM", 
        "filter_outliers_dict": {
            "filter_outliers": true, 
            "iterations": 2, 
            "std_devs": 2
        }, 
        "fit": "Parabolic", 
        "value": 77.97816042556038
    }, 
    "Ar40": {
        "error": 0.04622439402517703, 
        "error_type": "SEM", 
        "filter_outliers_dict": {
            "filter_outliers": true, 
            "iterations": 2, 
            "std_devs": 2
        }, 
        "fit": "Parabolic", 
        "value": 467.8461256706978
    }
}